json_secret_diary/__init__.py
json_secret_diary/json_secret_diary.py
json_secret_diary-1.0.4.2.dist-info/METADATA
json_secret_diary-1.0.4.2.dist-info/WHEEL
json_secret_diary-1.0.4.2.dist-info/entry_points.txt
json_secret_diary-1.0.4.2.dist-info/top_level.txt
json_secret_diary-1.0.4.2.dist-info/RECORD
