Metadata-Version: 2.1
Name: json-secret-diary
Version: 1.0.4.2
Summary: Simple secret diary based on JSON and AES encryption
Home-page: https://github.com/KingKaitoKid/secret_diary
Author: King Kaito Kid
Author-email: djstrix@me.com
License: UNKNOWN
Platform: UNKNOWN
Classifier: Programming Language :: Python :: 3
Classifier: License :: OSI Approved :: MIT License
Classifier: Operating System :: OS Independent
Requires-Python: >=3.6
Requires-Dist: pyAesCrypt
Requires-Dist: simplejson
Requires-Dist: requests
